md_snakeoil/__init__.py
md_snakeoil/apply.py
md_snakeoil/cli.py
md_snakeoil-0.1.6.dist-info/WHEEL
md_snakeoil-0.1.6.dist-info/entry_points.txt
md_snakeoil-0.1.6.dist-info/METADATA
md_snakeoil-0.1.6.dist-info/RECORD
