Metadata-Version: 2.4
Name: md-snakeoil
Version: 0.1.6
Summary: Format and lint Python code blocks within markdown files.
Author: Jakob Klotz
Author-email: Jakob Klotz <me@jakob-klotz.at>
License-Expression: MIT
Requires-Dist: ruff>=0.12.7
Requires-Dist: typer>=0.16.0
Requires-Python: >=3.11
